[
  {
    "title": "retro-kit-spotify",
    "path": "documents/Handige bestanden/retro-kit-spotify.pdf",
    "folder": "Handige bestanden",
    "tags": [],
    "fileType": "pdf",
    "lastModified": "2026-04-16T14:21:32.235Z"
  },
  {
    "title": "Hoe - Feedback en hulp",
    "path": "notes/Handige bestanden/Hoe - Feedback en hulp.md",
    "folder": "Handige bestanden",
    "tags": [],
    "fileType": "note",
    "lastModified": "2026-04-16T14:21:32.609Z"
  },
  {
    "title": "Wat is een leeruitkomst?",
    "path": "notes/Handige bestanden/Wat is een leeruitkomst?.md",
    "folder": "Handige bestanden",
    "tags": [],
    "fileType": "note",
    "lastModified": "2026-04-16T14:33:28.820Z"
  }
]